LICENSE
README.md
setup.py
py_xdb.egg-info/PKG-INFO
py_xdb.egg-info/SOURCES.txt
py_xdb.egg-info/dependency_links.txt
py_xdb.egg-info/entry_points.txt
py_xdb.egg-info/requires.txt
py_xdb.egg-info/top_level.txt
xdb/__init__.py
xdb/__main__.py
xdb/xdb.py