Metadata-Version: 2.1
Name: py-xdb
Version: 0.1.27
Summary: generic database client for CLI lovers
Home-page: https://github.com/walkerever/py-xdb
Author: Yonghang Wang
Author-email: wyhang@gmail.com
License: MIT License
Keywords: database,client,sql,CLI
Platform: UNKNOWN
Classifier: License :: OSI Approved :: Apache Software License
License-File: LICENSE
